slide_captcha/__init__.py
slide_captcha/slide.py
captchahub_slide_captcha-1.0.0.dist-info/METADATA
captchahub_slide_captcha-1.0.0.dist-info/WHEEL
captchahub_slide_captcha-1.0.0.dist-info/RECORD
